vexy_markliff/__init__.py
vexy_markliff/__version__.py
vexy_markliff/cli.py
vexy_markliff/config.py
vexy_markliff/exceptions.py
vexy_markliff/utils.py
vexy_markliff/core/__init__.py
vexy_markliff/core/converter.py
vexy_markliff/core/parser.py
vexy_markliff/models/__init__.py
vexy_markliff/models/xliff.py
vexy_markliff-1.3.1.dist-info/METADATA
vexy_markliff-1.3.1.dist-info/WHEEL
vexy_markliff-1.3.1.dist-info/entry_points.txt
vexy_markliff-1.3.1.dist-info/licenses/LICENSE
vexy_markliff-1.3.1.dist-info/RECORD
