Metadata-Version: 2.4
Name: vexy-markliff
Version: 1.3.1
Project-URL: Documentation, https://github.com/vexyart/vexy-markliff#readme
Project-URL: Issues, https://github.com/vexyart/vexy-markliff/issues
Project-URL: Source, https://github.com/vexyart/vexy-markliff
Author-email: Fontlab Ltd <opensource@vexy.art>
License: MIT
License-File: LICENSE
Classifier: Development Status :: 4 - Beta
Classifier: Intended Audience :: Developers
Classifier: License :: OSI Approved :: MIT License
Classifier: Operating System :: OS Independent
Classifier: Programming Language :: Python
Classifier: Programming Language :: Python :: 3.10
Classifier: Programming Language :: Python :: 3.11
Classifier: Programming Language :: Python :: 3.12
Classifier: Programming Language :: Python :: Implementation :: CPython
Classifier: Programming Language :: Python :: Implementation :: PyPy
Requires-Python: >=3.10
Requires-Dist: fire>=0.7.1
Requires-Dist: lxml>=6.0.2
Requires-Dist: markdown-it-py>=3.0.0
Requires-Dist: pydantic>=2.11.9
Requires-Dist: pyyaml>=6.0.2
Requires-Dist: rich>=14.1.0
Provides-Extra: all
Provides-Extra: dev
Requires-Dist: absolufy-imports>=0.3.1; extra == 'dev'
Requires-Dist: isort>=6.0.1; extra == 'dev'
Requires-Dist: mypy>=1.15.0; extra == 'dev'
Requires-Dist: pre-commit>=4.1.0; extra == 'dev'
Requires-Dist: pyupgrade>=3.19.1; extra == 'dev'
Requires-Dist: ruff>=0.9.7; extra == 'dev'
Provides-Extra: docs
Requires-Dist: myst-parser>=3.0.0; extra == 'docs'
Requires-Dist: sphinx-autodoc-typehints>=2.0.0; extra == 'docs'
Requires-Dist: sphinx-rtd-theme>=2.0.0; extra == 'docs'
Requires-Dist: sphinx>=7.2.6; extra == 'docs'
Provides-Extra: test
Requires-Dist: coverage[toml]>=7.6.12; extra == 'test'
Requires-Dist: pytest-cov>=6.0.0; extra == 'test'
Requires-Dist: pytest>=8.3.4; extra == 'test'
